scout/__init__.py
scout/main.py
gh_scout-0.3.2.dist-info/LICENSE
gh_scout-0.3.2.dist-info/METADATA
gh_scout-0.3.2.dist-info/WHEEL
gh_scout-0.3.2.dist-info/entry_points.txt
gh_scout-0.3.2.dist-info/top_level.txt
gh_scout-0.3.2.dist-info/RECORD
